[
   {
      "link_title": "@_Starry_Heavens ",
      "slug":"#",
      "items": [
         {
            "img": "https://webby-production.s3.amazonaws.com/Starry-Heavens/Home_2/instafeed-1.jpg",
            "slug": "#",
            "alt": "instagram",
            "insta_icon": "https://webby-production.s3.amazonaws.com/Starry-Heavens/Header/insta.svg"
         },
         {
            "img": "https://webby-production.s3.amazonaws.com/Starry-Heavens/Home_2/instafeed-2.jpg",
            "slug": "#",
            "alt": "instagram",
            "insta_icon": "https://webby-production.s3.amazonaws.com/Starry-Heavens/Header/insta.svg"
         },
         {
            "img": "https://webby-production.s3.amazonaws.com/Starry-Heavens/Home_2/instafeed-3.jpg",
            "slug": "#",
            "alt": "instagram",
            "insta_icon": "https://webby-production.s3.amazonaws.com/Starry-Heavens/Header/insta.svg"
         },
         {
            "img": "https://webby-production.s3.amazonaws.com/Starry-Heavens/Home_2/instafeed-4.jpg",
            "slug": "#",
            "alt": "instagram",
            "insta_icon": "https://webby-production.s3.amazonaws.com/Starry-Heavens/Header/insta.svg"
         },
         {
            "img": "https://webby-production.s3.amazonaws.com/Starry-Heavens/Home_2/instafeed-5.jpg",
            "slug": "#",
            "alt": "instagram",
            "insta_icon": "https://webby-production.s3.amazonaws.com/Starry-Heavens/Header/insta.svg"
         },
         {
            "img": "https://webby-production.s3.amazonaws.com/Starry-Heavens/Home_2/instafeed-6.jpg",
            "slug": "#",
            "alt": "instagram",
            "insta_icon": "https://webby-production.s3.amazonaws.com/Starry-Heavens/Header/insta.svg"
         }
      ]
   }
]