[
   {
      "filter": [
         {
            "categories": [
               {
                  "title": "Wedding Bracelet",
                  "count": "01",
                  "link": "/single-shop-v3"
               },
               {
                  "title": "Earring",
                  "count": "01",
                  "link": "/single-shop-v3"
               },
               {
                  "title": "Necklace",
                  "count": "01",
                  "link": "/single-shop-v3"
               },
               {
                  "title": "Gold Bangle",
                  "count": "01",
                  "link": "/single-shop-v3"
               },
               {
                  "title": "latest Ring",
                  "count": "01",
                  "link": "/single-shop-v3"
               },
               {
                  "title": "Belly Chain",
                  "count": "01",
                  "link": "/single-shop-v3"
               },
               {
                  "title": "Gemstone",
                  "count": "01",
                  "link": "/single-shop-v3"
               },
               {
                  "title": "Pendant",
                  "count": "01",
                  "link": "/single-shop-v3"
               },
               {
                  "title": "Locket",
                  "count": "01",
                  "link": "/single-shop-v3"
               },
               {
                  "title": "Brooch",
                  "count": "01",
                  "link": "/single-shop-v3"
               },
               {
                  "title": "uncategorized",
                  "count": "01",
                  "link": "/single-shop-v3"
               }
            ],
            "colors": [
               {
                  "icon": "https://webby-production.s3.amazonaws.com/Starry-Heavens/shop/blue-gradient.svg",
                  "slug": "/single-shop-v3",
                  "alt": "Blue",
                  "title": "Blue"
               },
               {
                  "icon": "https://webby-production.s3.amazonaws.com/Starry-Heavens/shop/green-gradient.svg",
                  "slug": "/single-shop-v3",
                  "alt": "Green",
                  "title": "Green"
               },
               {
                  "icon": "https://webby-production.s3.amazonaws.com/Starry-Heavens/shop/olive-gradient.svg",
                  "slug": "/single-shop-v3",
                  "alt": "Olive",
                  "title": "Olive"
               },
               {
                  "icon": "https://webby-production.s3.amazonaws.com/Starry-Heavens/shop/yellow-gradient.svg",
                  "slug": "/single-shop-v3",
                  "alt": "Yellow",
                  "title": "Yellow"
               },
               {
                  "icon": "https://webby-production.s3.amazonaws.com/Starry-Heavens/shop/brown-gradient.svg",
                  "slug": "/single-shop-v3",
                  "alt": "Brown",
                  "title": "Brown"
               },
               {
                  "icon": "https://webby-production.s3.amazonaws.com/Starry-Heavens/shop/orange-gradient.svg",
                  "slug": "/single-shop-v3",
                  "alt": "Orange",
                  "title": "Orange"
               },
               {
                  "icon": "https://webby-production.s3.amazonaws.com/Starry-Heavens/shop/red-gradient.svg",
                  "slug": "/single-shop-v3",
                  "alt": "Red",
                  "title": "Red"
               },
               {
                  "icon": "https://webby-production.s3.amazonaws.com/Starry-Heavens/shop/pink-gradient.svg",
                  "slug": "/single-shop-v3",
                  "alt": "Pink",
                  "title": "Pink"
               },
               {
                  "icon": "https://webby-production.s3.amazonaws.com/Starry-Heavens/shop/purple-gradient.svg",
                  "slug": "/single-shop-v3",
                  "alt": "Purple",
                  "title": "Purple"
               },
               {
                  "icon": "https://webby-production.s3.amazonaws.com/Starry-Heavens/shop/black-gradient.svg",
                  "slug": "/single-shop-v3",
                  "alt": "Black",
                  "title": "Black"
               },
               {
                  "icon": "https://webby-production.s3.amazonaws.com/Starry-Heavens/shop/white-gradient.svg",
                  "slug": "/single-shop-v3",
                  "alt": "White",
                  "title": "White"
               }
            ],
            "tags": [
               {
                  "title": "jewelry",
                  "link": "/single-shop-v3"
               },
               {
                  "title": "fashion",
                  "link": "/single-shop-v3"
               },
               {
                  "title": "jewellery",
                  "link": "/single-shop-v3"
               },
               {
                  "title": "handmade",
                  "link": "/single-shop-v3"
               },
               {
                  "title": "earrings",
                  "link": "/single-shop-v3"
               },
               {
                  "title": "gold",
                  "link": "/single-shop-v3"
               },
               {
                  "title": "accessories",
                  "link": "/single-shop-v3"
               },
               {
                  "title": "necklace",
                  "link": "/single-shop-v3"
               }
            ]
         }
      ],
      "products": [
         {
            "id": 96,
            "link": "/single-shop-v3",
            "img": "https://webby-production.s3.amazonaws.com/Starry-Heavens/shop/shop-pro-1.png",
            "title": "Diamonds Earring",
            "price": "589",
            "stock_badge": "Not Available",
            "sale_badge": "",
            "alt": "Golden bangles",
            "gia_number": "2466498019",
            "stock_id": "V80",
            "d_number": "64.5",
            "m_number": "7.93 - 7.89 * 5.10",
            "eyeclean": "-",
            "t_number": "58",
            "ratio": "1.01",
            "total": "$91.81",
            "price_ct": "$45.00",
            "company": "starry GEMS",
            "location": "INDIA",
            "shape": "Round",
            "ct": "0.25",
            "color": "D",
            "clarity": "VVS1",
            "cut": "EX",
            "pol": "EX",
            "sym": "EX",
            "flu": "None",
            "Lab": "GIA",
            "disc": "+ 21.90%",
            "wishlist_label": "Wishlist",
            "category": "Earrings",
            "shipped": "shipped",
            "btn_label": "View now",
            "box_class": "bg-white p-4 group xl:block lg:hidden",
            "short_des": "Lorem ipsum dolor sit amet, consectetur adipiscing elit, sed do eiusmod tempor incididunt ut labore et dolore magna aliqua. Ut enim ad minim veniam, quis nostrud exercitation ullamco laboris nisi ut aliquip commodo consequat. ",
            "badge": null,
            "icon_name": "cart",
            "filter_name": "earings "
         },
         {
            "id": 97,
            "link": "/single-shop-v3",
            "img": "https://webby-production.s3.amazonaws.com/Starry-Heavens/shop/shop-pro-2.png",
            "title": "Lumiere Ring ",
            "price": "790",
            "stock_badge": "Not Available",
            "sale_badge": "",
            "alt": "Golden bangles",
            "gia_number": "2466498019",
            "stock_id": "V80",
            "d_number": "64.5",
            "m_number": "7.93 - 7.89 * 5.10",
            "eyeclean": "-",
            "t_number": "58",
            "ratio": "1.01",
            "total": "$91.81",
            "price_ct": "$45.00",
            "company": "starry GEMS",
            "location": "INDIA",
            "shape": "Round",
            "ct": "0.25",
            "color": "D",
            "clarity": "VVS1",
            "cut": "EX",
            "pol": "EX",
            "sym": "EX",
            "flu": "None",
            "Lab": "GIA",
            "disc": "+ 21.90%",
            "wishlist_label": "Wishlist",
            "category": "Earrings",
            "shipped": "",
            "btn_label": "View now",
            "box_class": "bg-white p-4 group xl:block lg:hidden",
            "short_des": "Lorem ipsum dolor sit amet, consectetur adipiscing elit, sed do eiusmod tempor incididunt ut labore et dolore magna aliqua. Ut enim ad minim veniam, quis nostrud exercitation ullamco laboris nisi ut aliquip commodo consequat. ",
            "badge": null,
            "icon_name": "cart",
            "filter_name": "earings "
         },
         {
            "id": 98,
            "link": "/single-shop-v3",
            "img": "https://webby-production.s3.amazonaws.com/Starry-Heavens/shop/shop-pro-3.png",
            "title": "Women’s bracelet",
            "price": "329",
            "stock_badge": "Not Available",
            "sale_badge": "",
            "alt": "Golden bangles",
            "gia_number": "2466498019",
            "stock_id": "V80",
            "d_number": "64.5",
            "m_number": "7.93 - 7.89 * 5.10",
            "eyeclean": "-",
            "t_number": "58",
            "ratio": "1.01",
            "total": "$91.81",
            "price_ct": "$45.00",
            "company": "starry GEMS",
            "location": "INDIA",
            "shape": "Round",
            "ct": "0.25",
            "color": "D",
            "clarity": "VVS1",
            "cut": "EX",
            "pol": "EX",
            "sym": "EX",
            "flu": "None",
            "Lab": "GIA",
            "disc": "+ 21.90%",
            "wishlist_label": "Wishlist",
            "category": "Earrings",
            "shipped": "",
            "btn_label": "View now",
            "box_class": "bg-white p-4 group xl:block lg:hidden",
            "short_des": "Lorem ipsum dolor sit amet, consectetur adipiscing elit, sed do eiusmod tempor incididunt ut labore et dolore magna aliqua. Ut enim ad minim veniam, quis nostrud exercitation ullamco laboris nisi ut aliquip commodo consequat. ",
            "badge": "viewed",
            "icon_name": "cart",
            "filter_name": "earings "
         },
         {
            "id": 99,
            "link": "/single-shop-v3",
            "img": "https://webby-production.s3.amazonaws.com/Starry-Heavens/shop/shop-pro-4.png",
            "title": "diamond necklace",
            "price": "599",
            "stock_badge": "Not Available",
            "sale_badge": "",
            "alt": "Golden bangles",
            "gia_number": "2466498019",
            "stock_id": "V80",
            "d_number": "64.5",
            "m_number": "7.93 - 7.89 * 5.10",
            "eyeclean": "-",
            "t_number": "58",
            "ratio": "1.01",
            "total": "$91.81",
            "price_ct": "$45.00",
            "company": "starry GEMS",
            "location": "INDIA",
            "shape": "Round",
            "ct": "0.25",
            "color": "D",
            "clarity": "VVS1",
            "cut": "EX",
            "pol": "EX",
            "sym": "EX",
            "flu": "None",
            "Lab": "GIA",
            "disc": "+ 21.90%",
            "wishlist_label": "Wishlist",
            "category": "Earrings",
            "shipped": "shipped",
            "btn_label": "View now",
            "box_class": "bg-white p-4 group xl:block lg:hidden",
            "short_des": "Lorem ipsum dolor sit amet, consectetur adipiscing elit, sed do eiusmod tempor incididunt ut labore et dolore magna aliqua. Ut enim ad minim veniam, quis nostrud exercitation ullamco laboris nisi ut aliquip commodo consequat. ",
            "badge": null,
            "icon_name": "cart",
            "filter_name": "earings "
         },
         {
            "id": 100,
            "link": "/single-shop-v3",
            "img": "https://webby-production.s3.amazonaws.com/Starry-Heavens/shop/shop-pro-5.png",
            "title": " Women Gold bracelet ",
            "price": "599",
            "stock_badge": "Not Available",
            "sale_badge": "",
            "alt": "Golden bangles",
            "gia_number": "2466498019",
            "stock_id": "V80",
            "d_number": "64.5",
            "m_number": "7.93 - 7.89 * 5.10",
            "eyeclean": "-",
            "t_number": "58",
            "ratio": "1.01",
            "total": "$91.81",
            "price_ct": "$45.00",
            "company": "starry GEMS",
            "location": "INDIA",
            "shape": "Round",
            "ct": "0.25",
            "color": "D",
            "clarity": "VVS1",
            "cut": "EX",
            "pol": "EX",
            "sym": "EX",
            "flu": "None",
            "Lab": "GIA",
            "disc": "+ 21.90%",
            "wishlist_label": "Wishlist",
            "category": "Earrings",
            "shipped": "",
            "btn_label": "View now",
            "box_class": "bg-white p-4 group xl:block lg:hidden",
            "short_des": "Lorem ipsum dolor sit amet, consectetur adipiscing elit, sed do eiusmod tempor incididunt ut labore et dolore magna aliqua. Ut enim ad minim veniam, quis nostrud exercitation ullamco laboris nisi ut aliquip commodo consequat. ",
            "badge": "New",
            "icon_name": "cart",
            "filter_name": "earings "
         },
         {
            "id": 110,
            "link": "/single-shop-v3",
            "img": "https://webby-production.s3.amazonaws.com/Starry-Heavens/shop/shop-pro-6.png",
            "title": "Stylist pendant",
            "price": "449",
            "stock_badge": "Not Available",
            "sale_badge": "",
            "alt": "Golden bangles",
            "gia_number": "2466498019",
            "stock_id": "V80",
            "d_number": "64.5",
            "m_number": "7.93 - 7.89 * 5.10",
            "eyeclean": "-",
            "t_number": "58",
            "ratio": "1.01",
            "total": "$91.81",
            "price_ct": "$45.00",
            "company": "starry GEMS",
            "location": "INDIA",
            "shape": "Round",
            "ct": "0.25",
            "color": "D",
            "clarity": "VVS1",
            "cut": "EX",
            "pol": "EX",
            "sym": "EX",
            "flu": "None",
            "Lab": "GIA",
            "disc": "+ 21.90%",
            "wishlist_label": "Wishlist",
            "category": "Earrings",
            "shipped": "",
            "btn_label": "View now",
            "box_class": "bg-white p-4 group xl:block lg:hidden",
            "short_des": "Lorem ipsum dolor sit amet, consectetur adipiscing elit, sed do eiusmod tempor incididunt ut labore et dolore magna aliqua. Ut enim ad minim veniam, quis nostrud exercitation ullamco laboris nisi ut aliquip commodo consequat. ",
            "badge": "viewed",
            "icon_name": "cart",
            "filter_name": "earings "
         },
         {
            "id": 111,
            "link": "/single-shop-v3",
            "img": "https://webby-production.s3.amazonaws.com/Starry-Heavens/solitaire/solitare-img7.png",
            "title": "Elodie Solitaire ",
            "price": "768",
            "stock_badge": "Not Available",
            "sale_badge": "",
            "alt": "Golden bangles",
            "gia_number": "2466498019",
            "stock_id": "V80",
            "d_number": "64.5",
            "m_number": "7.93 - 7.89 * 5.10",
            "eyeclean": "-",
            "t_number": "58",
            "ratio": "1.01",
            "total": "$91.81",
            "price_ct": "$45.00",
            "company": "starry GEMS",
            "location": "INDIA",
            "shape": "Round",
            "ct": "0.25",
            "color": "D",
            "clarity": "VVS1",
            "cut": "EX",
            "pol": "EX",
            "sym": "EX",
            "flu": "None",
            "Lab": "GIA",
            "disc": "+ 21.90%",
            "wishlist_label": "Wishlist",
            "category": "Earrings",
            "shipped": "",
            "btn_label": "View now",
            "box_class": "bg-white p-4 group xl:block lg:hidden",
            "short_des": "Lorem ipsum dolor sit amet, consectetur adipiscing elit, sed do eiusmod tempor incididunt ut labore et dolore magna aliqua. Ut enim ad minim veniam, quis nostrud exercitation ullamco laboris nisi ut aliquip commodo consequat. ",
            "badge": null,
            "icon_name": "cart",
            "filter_name": "earings "
         },
         {
            "id": 112,
            "link": "/single-shop-v3",
            "img": "https://webby-production.s3.amazonaws.com/Starry-Heavens/shop/shop-pro-8.png",
            "title": "Gold bridal set",
            "price": "630",
            "stock_badge": "Not Available",
            "sale_badge": "",
            "alt": "Golden bangles",
            "gia_number": "2466498019",
            "stock_id": "V80",
            "d_number": "64.5",
            "m_number": "7.93 - 7.89 * 5.10",
            "eyeclean": "-",
            "t_number": "58",
            "ratio": "1.01",
            "total": "$91.81",
            "price_ct": "$45.00",
            "company": "starry GEMS",
            "location": "INDIA",
            "shape": "Round",
            "ct": "0.25",
            "color": "D",
            "clarity": "VVS1",
            "cut": "EX",
            "pol": "EX",
            "sym": "EX",
            "flu": "None",
            "Lab": "GIA",
            "disc": "+ 21.90%",
            "wishlist_label": "Wishlist",
            "category": "Earrings",
            "shipped": "shipped",
            "btn_label": "View now",
            "box_class": "bg-white p-4 group xl:block lg:hidden",
            "short_des": "Lorem ipsum dolor sit amet, consectetur adipiscing elit, sed do eiusmod tempor incididunt ut labore et dolore magna aliqua. Ut enim ad minim veniam, quis nostrud exercitation ullamco laboris nisi ut aliquip commodo consequat. ",
            "badge": null,
            "icon_name": "cart",
            "filter_name": "earings "
         },
         {
            "id": 113,
            "link": "/single-shop-v3",
            "img": "https://webby-production.s3.amazonaws.com/Starry-Heavens/shop/shop-pro-9.png",
            "title": "Petite Elodie Solitaire  ",
            "price": "565",
            "stock_badge": "Not Available",
            "sale_badge": "",
            "alt": "Golden bangles",
            "gia_number": "2466498019",
            "stock_id": "V80",
            "d_number": "64.5",
            "m_number": "7.93 - 7.89 * 5.10",
            "eyeclean": "-",
            "t_number": "58",
            "ratio": "1.01",
            "total": "$91.81",
            "price_ct": "$45.00",
            "company": "starry GEMS",
            "location": "INDIA",
            "shape": "Round",
            "ct": "0.25",
            "color": "D",
            "clarity": "VVS1",
            "cut": "EX",
            "pol": "EX",
            "sym": "EX",
            "flu": "None",
            "Lab": "GIA",
            "disc": "+ 21.90%",
            "wishlist_label": "Wishlist",
            "category": "Earrings",
            "shipped": "shipped",
            "btn_label": "View now",
            "box_class": "bg-white p-4 group xl:block lg:hidden",
            "short_des": "Lorem ipsum dolor sit amet, consectetur adipiscing elit, sed do eiusmod tempor incididunt ut labore et dolore magna aliqua. Ut enim ad minim veniam, quis nostrud exercitation ullamco laboris nisi ut aliquip commodo consequat. ",
            "badge": null,
            "icon_name": "cart",
            "filter_name": "earings "
         },
         {
            "id": 114,
            "link": "/single-shop-v3",
            "img": "https://webby-production.s3.amazonaws.com/Starry-Heavens/shop/shop-pro-10.png",
            "title": "22 carat golden Set",
            "price": "448",
            "stock_badge": "Not Available",
            "sale_badge": "",
            "alt": "Golden bangles",
            "gia_number": "2466498019",
            "stock_id": "V80",
            "d_number": "64.5",
            "m_number": "7.93 - 7.89 * 5.10",
            "eyeclean": "-",
            "t_number": "58",
            "ratio": "1.01",
            "total": "$91.81",
            "price_ct": "$45.00",
            "company": "starry GEMS",
            "location": "INDIA",
            "shape": "Round",
            "ct": "0.25",
            "color": "D",
            "clarity": "VVS1",
            "cut": "EX",
            "pol": "EX",
            "sym": "EX",
            "flu": "None",
            "Lab": "GIA",
            "disc": "+ 21.90%",
            "wishlist_label": "Wishlist",
            "category": "Earrings",
            "shipped": "",
            "btn_label": "View now",
            "box_class": "bg-white p-4 group xl:block lg:hidden",
            "short_des": "Lorem ipsum dolor sit amet, consectetur adipiscing elit, sed do eiusmod tempor incididunt ut labore et dolore magna aliqua. Ut enim ad minim veniam, quis nostrud exercitation ullamco laboris nisi ut aliquip commodo consequat. ",
            "badge": null,
            "icon_name": "cart",
            "filter_name": "earings "
         },
         {
            "id": 115,
            "link": "/single-shop-v3",
            "img": "https://webby-production.s3.amazonaws.com/Starry-Heavens/shop/shop-pro-11.png",
            "title": "engagement Ring",
            "price": "278",
            "stock_badge": "Not Available",
            "sale_badge": "",
            "alt": "Golden bangles",
            "gia_number": "2466498019",
            "stock_id": "V80",
            "d_number": "64.5",
            "m_number": "7.93 - 7.89 * 5.10",
            "eyeclean": "-",
            "t_number": "58",
            "ratio": "1.01",
            "total": "$91.81",
            "price_ct": "$45.00",
            "company": "starry GEMS",
            "location": "INDIA",
            "shape": "Round",
            "ct": "0.25",
            "color": "D",
            "clarity": "VVS1",
            "cut": "EX",
            "pol": "EX",
            "sym": "EX",
            "flu": "None",
            "Lab": "GIA",
            "disc": "+ 21.90%",
            "wishlist_label": "Wishlist",
            "category": "Earrings",
            "shipped": "",
            "btn_label": "View now",
            "box_class": "bg-white p-4 group xl:block lg:hidden",
            "short_des": "Lorem ipsum dolor sit amet, consectetur adipiscing elit, sed do eiusmod tempor incididunt ut labore et dolore magna aliqua. Ut enim ad minim veniam, quis nostrud exercitation ullamco laboris nisi ut aliquip commodo consequat. ",
            "badge": null,
            "icon_name": "cart",
            "filter_name": "earings "
         },
         {
            "id": 116,
            "link": "/single-shop-v3",
            "img": "https://webby-production.s3.amazonaws.com/Starry-Heavens/shop/shop-pro-12.png",
            "title": "gold Round bangle",
            "price": "429",
            "stock_badge": "Not Available",
            "sale_badge": "",
            "alt": "Golden bangles",
            "gia_number": "2466498019",
            "stock_id": "V80",
            "d_number": "64.5",
            "m_number": "7.93 - 7.89 * 5.10",
            "eyeclean": "-",
            "t_number": "58",
            "ratio": "1.01",
            "total": "$91.81",
            "price_ct": "$45.00",
            "company": "starry GEMS",
            "location": "INDIA",
            "shape": "Round",
            "ct": "0.25",
            "color": "D",
            "clarity": "VVS1",
            "cut": "EX",
            "pol": "EX",
            "sym": "EX",
            "flu": "None",
            "Lab": "GIA",
            "disc": "+ 21.90%",
            "wishlist_label": "Wishlist",
            "category": "Earrings",
            "shipped": "",
            "btn_label": "View now",
            "box_class": "bg-white p-4 group xl:block lg:hidden",
            "short_des": "Lorem ipsum dolor sit amet, consectetur adipiscing elit, sed do eiusmod tempor incididunt ut labore et dolore magna aliqua. Ut enim ad minim veniam, quis nostrud exercitation ullamco laboris nisi ut aliquip commodo consequat. ",
            "badge": "New",
            "icon_name": "cart",
            "filter_name": "earings "
         },
         {
            "id": 117,
            "link": "/single-shop-v3",
            "img": "https://webby-production.s3.amazonaws.com/Starry-Heavens/shop/shop-pro-13.png",
            "title": "Secret Halo Ring",
            "price": "990",
            "stock_badge": "Not Available",
            "sale_badge": "",
            "alt": "Golden bangles",
            "gia_number": "2466498019",
            "stock_id": "V80",
            "d_number": "64.5",
            "m_number": "7.93 - 7.89 * 5.10",
            "eyeclean": "-",
            "t_number": "58",
            "ratio": "1.01",
            "total": "$91.81",
            "price_ct": "$45.00",
            "company": "starry GEMS",
            "location": "INDIA",
            "shape": "Round",
            "ct": "0.25",
            "color": "D",
            "clarity": "VVS1",
            "cut": "EX",
            "pol": "EX",
            "sym": "EX",
            "flu": "None",
            "Lab": "GIA",
            "disc": "+ 21.90%",
            "wishlist_label": "Wishlist",
            "category": "Earrings",
            "shipped": "shipped",
            "btn_label": "View now",
            "box_class": "bg-white p-4 group xl:block lg:hidden",
            "short_des": "Lorem ipsum dolor sit amet, consectetur adipiscing elit, sed do eiusmod tempor incididunt ut labore et dolore magna aliqua. Ut enim ad minim veniam, quis nostrud exercitation ullamco laboris nisi ut aliquip commodo consequat. ",
            "badge": null,
            "icon_name": "cart",
            "filter_name": "earings "
         },
         {
            "id": 118,
            "link": "/single-shop-v3",
            "img": "https://webby-production.s3.amazonaws.com/Starry-Heavens/shop/shop-pro-14.png",
            "title": "Gold Diamond Ring",
            "price": "719",
            "stock_badge": "Not Available",
            "sale_badge": "",
            "alt": "Golden bangles",
            "gia_number": "2466498019",
            "stock_id": "V80",
            "d_number": "64.5",
            "m_number": "7.93 - 7.89 * 5.10",
            "eyeclean": "-",
            "t_number": "58",
            "ratio": "1.01",
            "total": "$91.81",
            "price_ct": "$45.00",
            "company": "starry GEMS",
            "location": "INDIA",
            "shape": "Round",
            "ct": "0.25",
            "color": "D",
            "clarity": "VVS1",
            "cut": "EX",
            "pol": "EX",
            "sym": "EX",
            "flu": "None",
            "Lab": "GIA",
            "disc": "+ 21.90%",
            "wishlist_label": "Wishlist",
            "category": "Earrings",
            "shipped": "",
            "btn_label": "View now",
            "box_class": "bg-white p-4 group xl:block lg:hidden",
            "short_des": "Lorem ipsum dolor sit amet, consectetur adipiscing elit, sed do eiusmod tempor incididunt ut labore et dolore magna aliqua. Ut enim ad minim veniam, quis nostrud exercitation ullamco laboris nisi ut aliquip commodo consequat. ",
            "badge": null,
            "icon_name": "cart",
            "filter_name": "earings "
         },
         {
            "id": 119,
            "link": "/single-shop-v3",
            "img": "https://webby-production.s3.amazonaws.com/Starry-Heavens/shop/shop-pro-15.png",
            "title": "gems earrings",
            "price": "880",
            "stock_badge": "Not Available",
            "sale_badge": "",
            "alt": "Golden bangles",
            "gia_number": "2466498019",
            "stock_id": "V80",
            "d_number": "64.5",
            "m_number": "7.93 - 7.89 * 5.10",
            "eyeclean": "-",
            "t_number": "58",
            "ratio": "1.01",
            "total": "$91.81",
            "price_ct": "$45.00",
            "company": "starry GEMS",
            "location": "INDIA",
            "shape": "Round",
            "ct": "0.25",
            "color": "D",
            "clarity": "VVS1",
            "cut": "EX",
            "pol": "EX",
            "sym": "EX",
            "flu": "None",
            "Lab": "GIA",
            "disc": "+ 21.90%",
            "wishlist_label": "Wishlist",
            "category": "Earrings",
            "shipped": "shipped",
            "btn_label": "View now",
            "box_class": "bg-white p-4 group xl:block lg:hidden",
            "short_des": "Lorem ipsum dolor sit amet, consectetur adipiscing elit, sed do eiusmod tempor incididunt ut labore et dolore magna aliqua. Ut enim ad minim veniam, quis nostrud exercitation ullamco laboris nisi ut aliquip commodo consequat. ",
            "badge": null,
            "icon_name": "cart",
            "filter_name": "earings "
         },
         {
            "id": 120,
            "link": "/single-shop-v3",
            "img": "https://webby-production.s3.amazonaws.com/Starry-Heavens/shop/shop-pro-16.png",
            "title": " Delilah Twist Solitaire",
            "price": "288",
            "stock_badge": "Not Available",
            "sale_badge": "",
            "alt": "Golden bangles",
            "gia_number": "2466498019",
            "stock_id": "V80",
            "d_number": "64.5",
            "m_number": "7.93 - 7.89 * 5.10",
            "eyeclean": "-",
            "t_number": "58",
            "ratio": "1.01",
            "total": "$91.81",
            "price_ct": "$45.00",
            "company": "starry GEMS",
            "location": "INDIA",
            "shape": "Round",
            "ct": "0.25",
            "color": "D",
            "clarity": "VVS1",
            "cut": "EX",
            "pol": "EX",
            "sym": "EX",
            "flu": "None",
            "Lab": "GIA",
            "disc": "+ 21.90%",
            "wishlist_label": "Wishlist",
            "category": "Earrings",
            "shipped": "",
            "btn_label": "View now",
            "box_class": "bg-white p-4 group xl:block lg:hidden",
            "short_des": "Lorem ipsum dolor sit amet, consectetur adipiscing elit, sed do eiusmod tempor incididunt ut labore et dolore magna aliqua. Ut enim ad minim veniam, quis nostrud exercitation ullamco laboris nisi ut aliquip commodo consequat. ",
            "badge": "viewed",
            "icon_name": "cart",
            "filter_name": "earings "
         }
      ]
   }
]